PyQt6/Qt6/qsci/api/python/PyQt6-Charts.api
PyQt6/QtCharts.abi3.so
PyQt6/QtCharts.pyi
PyQt6/bindings/QtCharts/QtCharts.toml
PyQt6/bindings/QtCharts/QtChartsmod.sip
PyQt6/bindings/QtCharts/qabstractaxis.sip
PyQt6/bindings/QtCharts/qabstractbarseries.sip
PyQt6/bindings/QtCharts/qabstractseries.sip
PyQt6/bindings/QtCharts/qarealegendmarker.sip
PyQt6/bindings/QtCharts/qareaseries.sip
PyQt6/bindings/QtCharts/qbarcategoryaxis.sip
PyQt6/bindings/QtCharts/qbarlegendmarker.sip
PyQt6/bindings/QtCharts/qbarseries.sip
PyQt6/bindings/QtCharts/qbarset.sip
PyQt6/bindings/QtCharts/qboxplotlegendmarker.sip
PyQt6/bindings/QtCharts/qboxplotseries.sip
PyQt6/bindings/QtCharts/qboxset.sip
PyQt6/bindings/QtCharts/qcandlesticklegendmarker.sip
PyQt6/bindings/QtCharts/qcandlestickmodelmapper.sip
PyQt6/bindings/QtCharts/qcandlestickseries.sip
PyQt6/bindings/QtCharts/qcandlestickset.sip
PyQt6/bindings/QtCharts/qcategoryaxis.sip
PyQt6/bindings/QtCharts/qchart.sip
PyQt6/bindings/QtCharts/qchartview.sip
PyQt6/bindings/QtCharts/qcoloraxis.sip
PyQt6/bindings/QtCharts/qdatetimeaxis.sip
PyQt6/bindings/QtCharts/qhash.sip
PyQt6/bindings/QtCharts/qhbarmodelmapper.sip
PyQt6/bindings/QtCharts/qhboxplotmodelmapper.sip
PyQt6/bindings/QtCharts/qhcandlestickmodelmapper.sip
PyQt6/bindings/QtCharts/qhorizontalbarseries.sip
PyQt6/bindings/QtCharts/qhorizontalpercentbarseries.sip
PyQt6/bindings/QtCharts/qhorizontalstackedbarseries.sip
PyQt6/bindings/QtCharts/qhpiemodelmapper.sip
PyQt6/bindings/QtCharts/qhxymodelmapper.sip
PyQt6/bindings/QtCharts/qlegend.sip
PyQt6/bindings/QtCharts/qlegendmarker.sip
PyQt6/bindings/QtCharts/qlineseries.sip
PyQt6/bindings/QtCharts/qlogvalueaxis.sip
PyQt6/bindings/QtCharts/qpercentbarseries.sip
PyQt6/bindings/QtCharts/qpielegendmarker.sip
PyQt6/bindings/QtCharts/qpieseries.sip
PyQt6/bindings/QtCharts/qpieslice.sip
PyQt6/bindings/QtCharts/qpolarchart.sip
PyQt6/bindings/QtCharts/qscatterseries.sip
PyQt6/bindings/QtCharts/qsplineseries.sip
PyQt6/bindings/QtCharts/qstackedbarseries.sip
pyqt6_charts-6.10.0.dist-info/licenses/LICENSE
pyqt6_charts-6.10.0.dist-info/WHEEL
pyqt6_charts-6.10.0.dist-info/METADATA
pyqt6_charts-6.10.0.dist-info/RECORD
